bot_station_client/__init__.py
bot_station_client/client.py
bot_station_client/model/__init__.py
bot_station_client/model/call_result.py
bot_station_client/model/config.py
bot_station_client/model/document.py
tests/__init__.py
tests/bot_station_client_e2e_test.py
bot_station_client-0.1.0.dist-info/LICENSE
bot_station_client-0.1.0.dist-info/METADATA
bot_station_client-0.1.0.dist-info/WHEEL
bot_station_client-0.1.0.dist-info/top_level.txt
bot_station_client-0.1.0.dist-info/RECORD
