Metadata-Version: 2.1
Name: bot_station_client
Version: 0.1.0
Summary: Bot Station client SDK
Author: Maxim Marashan
Classifier: Programming Language :: Python :: 3.8
Classifier: License :: OSI Approved :: MIT License
Classifier: Operating System :: OS Independent
Requires-Python: >=3.8
License-File: LICENSE
Requires-Dist: requests ==2.31.0
Requires-Dist: aiohttp ==3.9.3
